LICENSE
MANIFEST.in
README.rst
setup.py
django_translatable_fields.egg-info/PKG-INFO
django_translatable_fields.egg-info/SOURCES.txt
django_translatable_fields.egg-info/dependency_links.txt
django_translatable_fields.egg-info/not-zip-safe
django_translatable_fields.egg-info/requires.txt
django_translatable_fields.egg-info/top_level.txt
translatable_fields/__init__.py
translatable_fields/models.py
translatable_fields/value.py
translatable_fields/widgets.py
translatable_fields/static/translatable_fields/translatable_fields.css
translatable_fields/static/translatable_fields/translatable_fields.js
translatable_fields/templates/translatable_fields/multiwidget.html